hytale/__init__.py
hytale/_version.py
hytale/account_client.py
hytale/blogs.py
hytale/exceptions.py
hytale/http.py
hytale/media.py
hytale/packages.py
hytale/status.py
hytale/models/base.py
hytale/models/package.py
hytale/models/status.py
hytale/models/blogs/blog_post.py
hytale/models/blogs/blog_post_excerpt.py
hytale/models/blogs/cover_image.py
hytale/models/media/category.py
hytale/models/media/image.py
hytale/models/media/media.py
hytale/models/media/video.py
hytale_api-2.0.0.dist-info/licenses/LICENSE
hytale_api-2.0.0.dist-info/METADATA
hytale_api-2.0.0.dist-info/WHEEL
hytale_api-2.0.0.dist-info/top_level.txt
hytale_api-2.0.0.dist-info/RECORD
